align_evals_optimizer/__init__.py
align_evals_optimizer/optimizer.py
align_evals_optimizer-0.0.2.dist-info/METADATA
align_evals_optimizer-0.0.2.dist-info/WHEEL
align_evals_optimizer-0.0.2.dist-info/top_level.txt
align_evals_optimizer-0.0.2.dist-info/RECORD
