Metadata-Version: 2.4
Name: align_evals_optimizer
Version: 0.0.2
Summary: A pytjo
Author-email: Isaac Hershenson <isaac@langchain.dev>
Requires-Python: >=3.8
Requires-Dist: langsmith
Requires-Dist: requests
Requires-Dist: langchain-core
Requires-Dist: pydantic
Requires-Dist: langchain
